{"GlobalPropertiesHash":"/6TwEZT+hC+9MM0MfbbKH8F70uo/sunc6AcPnhoNVyc=","FingerprintPatternsHash":"gq3WsqcKBUGTSNle7RKKyXRIwh7M8ccEqOqYvIzoM04=","PropertyOverridesHash":"8ZRc1sGeVrPBx4lD717BgRaQekyh78QKV9SKsdt638U=","InputHashes":["AwAA/MoGpkMCKdf5p1bcUc75Mh563i8L2OUbhXm2fBk=","kLfegri17WpZ2y9aa9v4Ik4iiRzDudFdgjOtUfBgiVk=","0NmDEbYSBKBCPPCcQ\u002BtfSxdDeW36V0\u002BaEHcS7khVF8Q=","4SFvSm73IcCSuXGkLEYntft9qqDiAkv0U6IAvTS2NPs=","iNsjkodyBPc1dm12TcIBucJWrhdN5rYa4E9Um224x9s=","X8R3ZTN6jTZXaiPTdIEBYcb5HoweQo00V\u002B/2RCq265A=","14xlGT72aLKEDG4cJRChtDudY9r7pm0KTKKViRMPjXE="],"CachedAssets":{"AwAA/MoGpkMCKdf5p1bcUc75Mh563i8L2OUbhXm2fBk=":{"Identity":"T:\\Projects\\Code\\C#\\apps\\cgshop\\cgshop\\wwwroot\\css\\app.css","SourceId":"cgshop","SourceType":"Discovered","ContentRoot":"T:\\Projects\\Code\\C#\\apps\\cgshop\\cgshop\\wwwroot\\","BasePath":"cgshop","RelativePath":"css/app#[.{fingerprint}]?.css","AssetKind":"All","AssetMode":"All","AssetRole":"Primary","AssetMergeBehavior":null,"AssetMergeSource":"","RelatedAsset":null,"AssetTraitName":null,"AssetTraitValue":null,"Fingerprint":"81sotqnb8s","Integrity":"FEcjGL5Vayj/vVFfza9Fl7AOyv/PLNTZoBBgB6QciYc=","CopyToOutputDirectory":"Never","CopyToPublishDirectory":"PreserveNewest","OriginalItemSpec":"wwwroot\\css\\app.css","FileLength":3677,"LastWriteTime":"2026-07-06T21:32:22.0909831+00:00"},"kLfegri17WpZ2y9aa9v4Ik4iiRzDudFdgjOtUfBgiVk=":{"Identity":"T:\\Projects\\Code\\C#\\apps\\cgshop\\cgshop\\wwwroot\\icon-192.png","SourceId":"cgshop","SourceType":"Discovered","ContentRoot":"T:\\Projects\\Code\\C#\\apps\\cgshop\\cgshop\\wwwroot\\","BasePath":"cgshop","RelativePath":"icon-192#[.{fingerprint}]?.png","AssetKind":"All","AssetMode":"All","AssetRole":"Primary","AssetMergeBehavior":null,"AssetMergeSource":"","RelatedAsset":null,"AssetTraitName":null,"AssetTraitValue":null,"Fingerprint":"f9uvjujlxy","Integrity":"DbpQaq68ZSb5IoPosBErM1QWBfsbTxpJqhU0REi6wP4=","CopyToOutputDirectory":"Never","CopyToPublishDirectory":"PreserveNewest","OriginalItemSpec":"wwwroot\\icon-192.png","FileLength":2626,"LastWriteTime":"2026-07-06T21:32:22.0995879+00:00"},"0NmDEbYSBKBCPPCcQ\u002BtfSxdDeW36V0\u002BaEHcS7khVF8Q=":{"Identity":"T:\\Projects\\Code\\C#\\apps\\cgshop\\cgshop\\wwwroot\\index.html","SourceId":"cgshop","SourceType":"Discovered","ContentRoot":"T:\\Projects\\Code\\C#\\apps\\cgshop\\cgshop\\wwwroot\\","BasePath":"cgshop","RelativePath":"index#[.{fingerprint}]?.html","AssetKind":"All","AssetMode":"All","AssetRole":"Primary","AssetMergeBehavior":null,"AssetMergeSource":"","RelatedAsset":null,"AssetTraitName":null,"AssetTraitValue":null,"Fingerprint":"lx4m4c0h2k","Integrity":"eTZ681SrnjYfrsVurYJq/25577yOccT132p5SRZeS88=","CopyToOutputDirectory":"Never","CopyToPublishDirectory":"PreserveNewest","OriginalItemSpec":"wwwroot\\index.html","FileLength":918,"LastWriteTime":"2026-07-07T01:12:56.4803977+00:00"}},"CachedCopyCandidates":{}}